[
  {
    "epoch": 10,
    "value": 18634.3877
  },
  {
    "epoch": 20,
    "value": 18634.3877
  },
  {
    "epoch": 30,
    "value": 18447.3545
  },
  {
    "epoch": 40,
    "value": 18447.3545
  },
  {
    "epoch": 50,
    "value": 18447.3545
  },
  {
    "epoch": 60,
    "value": 18447.3545
  },
  {
    "epoch": 70,
    "value": 18447.3545
  },
  {
    "epoch": 80,
    "value": 18447.3545
  },
  {
    "epoch": 90,
    "value": 18447.3545
  },
  {
    "epoch": 100,
    "value": 18447.3545
  }
]