[
  {
    "epoch": 10,
    "value": 19037.3063
  },
  {
    "epoch": 20,
    "value": 19037.3063
  },
  {
    "epoch": 30,
    "value": 16904.7617
  },
  {
    "epoch": 40,
    "value": 16904.7617
  },
  {
    "epoch": 50,
    "value": 16039.3324
  },
  {
    "epoch": 60,
    "value": 16039.3324
  },
  {
    "epoch": 70,
    "value": 15789.7119
  },
  {
    "epoch": 80,
    "value": 15789.7119
  },
  {
    "epoch": 90,
    "value": 15634.0796
  },
  {
    "epoch": 100,
    "value": 15634.0796
  }
]